mcp_server_git/__init__.py
mcp_server_git/__main__.py
mcp_server_git/py.typed
mcp_server_git/server.py
mcp_server_git-2025.12.18.dist-info/METADATA
mcp_server_git-2025.12.18.dist-info/WHEEL
mcp_server_git-2025.12.18.dist-info/entry_points.txt
mcp_server_git-2025.12.18.dist-info/licenses/LICENSE
mcp_server_git-2025.12.18.dist-info/RECORD
